{
  "metadata": {
    "createdAtUtcTimeIso": "2021-11-13T08:14:29.002Z",
    "updatedAtUtcTimeIso": "2021-11-13T08:14:29.002Z"
  },
  "data": {
    "vaccinationsPerDhb": [
      {
        "dhbName": "Northland",
        "firstDoses": 129907,
        "firstDosesPercentageRaw": "81%",
        "firstDosesTo90Percent": 15281,
        "secondDoses": 108668,
        "secondDosesPercentageRaw": "67%",
        "secondDosesTo90Percent": 36520,
        "totalPopulation": 161320
      },
      {
        "dhbName": "Waitemata",
        "firstDoses": 482909,
        "firstDosesPercentageRaw": "92%",
        "firstDosesTo90Percent": 0,
        "secondDoses": 435139,
        "secondDosesPercentageRaw": "83%",
        "secondDosesTo90Percent": 38339,
        "totalPopulation": 526087
      },
      {
        "dhbName": "Auckland",
        "firstDoses": 400479,
        "firstDosesPercentageRaw": "94%",
        "firstDosesTo90Percent": 0,
        "secondDoses": 366278,
        "secondDosesPercentageRaw": "86%",
        "secondDosesTo90Percent": 15284,
        "totalPopulation": 423958
      },
      {
        "dhbName": "Counties Manukau",
        "firstDoses": 433242,
        "firstDosesPercentageRaw": "90%",
        "firstDosesTo90Percent": 1254,
        "secondDoses": 382391,
        "secondDosesPercentageRaw": "79%",
        "secondDosesTo90Percent": 52105,
        "totalPopulation": 482773
      },
      {
        "dhbName": "Waikato",
        "firstDoses": 313302,
        "firstDosesPercentageRaw": "88%",
        "firstDosesTo90Percent": 8156,
        "secondDoses": 268235,
        "secondDosesPercentageRaw": "75%",
        "secondDosesTo90Percent": 53223,
        "totalPopulation": 357176
      },
      {
        "dhbName": "Lakes",
        "firstDoses": 77180,
        "firstDosesPercentageRaw": "82%",
        "firstDosesTo90Percent": 7797,
        "secondDoses": 64515,
        "secondDosesPercentageRaw": "68%",
        "secondDosesTo90Percent": 20462,
        "totalPopulation": 94419
      },
      {
        "dhbName": "Bay of Plenty",
        "firstDoses": 182323,
        "firstDosesPercentageRaw": "84%",
        "firstDosesTo90Percent": 12924,
        "secondDoses": 153099,
        "secondDosesPercentageRaw": "71%",
        "secondDosesTo90Percent": 42148,
        "totalPopulation": 216941
      },
      {
        "dhbName": "Tairawhiti",
        "firstDoses": 33438,
        "firstDosesPercentageRaw": "80%",
        "firstDosesTo90Percent": 4330,
        "secondDoses": 27529,
        "secondDosesPercentageRaw": "66%",
        "secondDosesTo90Percent": 10240,
        "totalPopulation": 41965
      },
      {
        "dhbName": "Taranaki",
        "firstDoses": 87049,
        "firstDosesPercentageRaw": "85%",
        "firstDosesTo90Percent": 4883,
        "secondDoses": 70974,
        "secondDosesPercentageRaw": "69%",
        "secondDosesTo90Percent": 20958,
        "totalPopulation": 102147
      },
      {
        "dhbName": "Hawkes Bay",
        "firstDoses": 124478,
        "firstDosesPercentageRaw": "86%",
        "firstDosesTo90Percent": 6536,
        "secondDoses": 106471,
        "secondDosesPercentageRaw": "73%",
        "secondDosesTo90Percent": 24543,
        "totalPopulation": 145571
      },
      {
        "dhbName": "MidCentral",
        "firstDoses": 132922,
        "firstDosesPercentageRaw": "87%",
        "firstDosesTo90Percent": 4150,
        "secondDoses": 113665,
        "secondDosesPercentageRaw": "75%",
        "secondDosesTo90Percent": 23407,
        "totalPopulation": 152302
      },
      {
        "dhbName": "Whanganui",
        "firstDoses": 46784,
        "firstDosesPercentageRaw": "82%",
        "firstDosesTo90Percent": 4738,
        "secondDoses": 40256,
        "secondDosesPercentageRaw": "70%",
        "secondDosesTo90Percent": 11266,
        "totalPopulation": 57247
      },
      {
        "dhbName": "Capital and Coast",
        "firstDoses": 251431,
        "firstDosesPercentageRaw": "93%",
        "firstDosesTo90Percent": 0,
        "secondDoses": 224666,
        "secondDosesPercentageRaw": "83%",
        "secondDosesTo90Percent": 19391,
        "totalPopulation": 271174
      },
      {
        "dhbName": "Hutt Valley",
        "firstDoses": 115606,
        "firstDosesPercentageRaw": "89%",
        "firstDosesTo90Percent": 1609,
        "secondDoses": 100608,
        "secondDosesPercentageRaw": "77%",
        "secondDosesTo90Percent": 16607,
        "totalPopulation": 130239
      },
      {
        "dhbName": "Wairarapa",
        "firstDoses": 35836,
        "firstDosesPercentageRaw": "87%",
        "firstDosesTo90Percent": 1448,
        "secondDoses": 30908,
        "secondDosesPercentageRaw": "75%",
        "secondDosesTo90Percent": 6376,
        "totalPopulation": 41427
      },
      {
        "dhbName": "Nelson Marlborough",
        "firstDoses": 118950,
        "firstDosesPercentageRaw": "88%",
        "firstDosesTo90Percent": 3219,
        "secondDoses": 105163,
        "secondDosesPercentageRaw": "77%",
        "secondDosesTo90Percent": 17006,
        "totalPopulation": 135743
      },
      {
        "dhbName": "West Coast",
        "firstDoses": 23119,
        "firstDosesPercentageRaw": "83%",
        "firstDosesTo90Percent": 1996,
        "secondDoses": 19403,
        "secondDosesPercentageRaw": "70%",
        "secondDosesTo90Percent": 5712,
        "totalPopulation": 27906
      },
      {
        "dhbName": "Canterbury",
        "firstDoses": 445643,
        "firstDosesPercentageRaw": "92%",
        "firstDosesTo90Percent": 0,
        "secondDoses": 373503,
        "secondDosesPercentageRaw": "77%",
        "secondDosesTo90Percent": 61098,
        "totalPopulation": 482890
      },
      {
        "dhbName": "South Canterbury",
        "firstDoses": 46084,
        "firstDosesPercentageRaw": "88%",
        "firstDosesTo90Percent": 1242,
        "secondDoses": 40424,
        "secondDosesPercentageRaw": "77%",
        "secondDosesTo90Percent": 6902,
        "totalPopulation": 52584
      },
      {
        "dhbName": "Southern",
        "firstDoses": 261973,
        "firstDosesPercentageRaw": "91%",
        "firstDosesTo90Percent": 0,
        "secondDoses": 229645,
        "secondDosesPercentageRaw": "80%",
        "secondDosesTo90Percent": 29568,
        "totalPopulation": 288015
      },
      {
        "dhbName": "Overseas / Unknown",
        "firstDoses": 2047,
        "firstDosesPercentageRaw": "12%",
        "firstDosesTo90Percent": 13409,
        "secondDoses": 1720,
        "secondDosesPercentageRaw": "10%",
        "secondDosesTo90Percent": 13736,
        "totalPopulation": 17173
      }
    ],
    "dataValidAsAtNzTimeIso": "2021-11-05T23:59:00.000+13:00"
  }
}