{
  "metadata": {
    "createdAtUtcTimeIso": "2021-12-20T00:01:38.923Z",
    "updatedAtUtcTimeIso": "2021-12-20T00:01:38.923Z"
  },
  "data": {
    "vaccinationsPerDhb": [
      {
        "dhbName": "Northland",
        "firstDoses": 142077,
        "firstDosesPercentageRaw": "88%",
        "firstDosesTo90Percent": 3111,
        "secondDoses": 133231,
        "secondDosesPercentageRaw": "83%",
        "secondDosesTo90Percent": 11957,
        "totalPopulation": 161320
      },
      {
        "dhbName": "Waitemata",
        "firstDoses": 499743,
        "firstDosesPercentageRaw": "95%",
        "firstDosesTo90Percent": 0,
        "secondDoses": 486695,
        "secondDosesPercentageRaw": "93%",
        "secondDosesTo90Percent": 0,
        "totalPopulation": 526087
      },
      {
        "dhbName": "Auckland",
        "firstDoses": 413917,
        "firstDosesPercentageRaw": "98%",
        "firstDosesTo90Percent": 0,
        "secondDoses": 403732,
        "secondDosesPercentageRaw": "95%",
        "secondDosesTo90Percent": 0,
        "totalPopulation": 423958
      },
      {
        "dhbName": "Counties Manukau",
        "firstDoses": 455135,
        "firstDosesPercentageRaw": "94%",
        "firstDosesTo90Percent": 0,
        "secondDoses": 438370,
        "secondDosesPercentageRaw": "91%",
        "secondDosesTo90Percent": 0,
        "totalPopulation": 482773
      },
      {
        "dhbName": "Waikato",
        "firstDoses": 332981,
        "firstDosesPercentageRaw": "93%",
        "firstDosesTo90Percent": 0,
        "secondDoses": 317332,
        "secondDosesPercentageRaw": "89%",
        "secondDosesTo90Percent": 4126,
        "totalPopulation": 357176
      },
      {
        "dhbName": "Lakes",
        "firstDoses": 86308,
        "firstDosesPercentageRaw": "91%",
        "firstDosesTo90Percent": 0,
        "secondDoses": 80890,
        "secondDosesPercentageRaw": "86%",
        "secondDosesTo90Percent": 4087,
        "totalPopulation": 94419
      },
      {
        "dhbName": "Bay of Plenty",
        "firstDoses": 201393,
        "firstDosesPercentageRaw": "93%",
        "firstDosesTo90Percent": 0,
        "secondDoses": 189509,
        "secondDosesPercentageRaw": "87%",
        "secondDosesTo90Percent": 5738,
        "totalPopulation": 216941
      },
      {
        "dhbName": "Tairawhiti",
        "firstDoses": 37969,
        "firstDosesPercentageRaw": "90%",
        "firstDosesTo90Percent": 0,
        "secondDoses": 35149,
        "secondDosesPercentageRaw": "84%",
        "secondDosesTo90Percent": 2620,
        "totalPopulation": 41965
      },
      {
        "dhbName": "Taranaki",
        "firstDoses": 94580,
        "firstDosesPercentageRaw": "93%",
        "firstDosesTo90Percent": 0,
        "secondDoses": 89459,
        "secondDosesPercentageRaw": "88%",
        "secondDosesTo90Percent": 2473,
        "totalPopulation": 102147
      },
      {
        "dhbName": "Hawkes Bay",
        "firstDoses": 136934,
        "firstDosesPercentageRaw": "94%",
        "firstDosesTo90Percent": 0,
        "secondDoses": 129024,
        "secondDosesPercentageRaw": "89%",
        "secondDosesTo90Percent": 1990,
        "totalPopulation": 145571
      },
      {
        "dhbName": "MidCentral",
        "firstDoses": 144266,
        "firstDosesPercentageRaw": "95%",
        "firstDosesTo90Percent": 0,
        "secondDoses": 137066,
        "secondDosesPercentageRaw": "90%",
        "secondDosesTo90Percent": 6,
        "totalPopulation": 152302
      },
      {
        "dhbName": "Whanganui",
        "firstDoses": 51631,
        "firstDosesPercentageRaw": "90%",
        "firstDosesTo90Percent": 0,
        "secondDoses": 48555,
        "secondDosesPercentageRaw": "85%",
        "secondDosesTo90Percent": 2967,
        "totalPopulation": 57247
      },
      {
        "dhbName": "Capital and Coast",
        "firstDoses": 263537,
        "firstDosesPercentageRaw": "97%",
        "firstDosesTo90Percent": 0,
        "secondDoses": 256213,
        "secondDosesPercentageRaw": "94%",
        "secondDosesTo90Percent": 0,
        "totalPopulation": 271174
      },
      {
        "dhbName": "Hutt Valley",
        "firstDoses": 124025,
        "firstDosesPercentageRaw": "95%",
        "firstDosesTo90Percent": 0,
        "secondDoses": 118955,
        "secondDosesPercentageRaw": "91%",
        "secondDosesTo90Percent": 0,
        "totalPopulation": 130239
      },
      {
        "dhbName": "Wairarapa",
        "firstDoses": 39223,
        "firstDosesPercentageRaw": "95%",
        "firstDosesTo90Percent": 0,
        "secondDoses": 37360,
        "secondDosesPercentageRaw": "90%",
        "secondDosesTo90Percent": 0,
        "totalPopulation": 41427
      },
      {
        "dhbName": "Nelson Marlborough",
        "firstDoses": 128203,
        "firstDosesPercentageRaw": "94%",
        "firstDosesTo90Percent": 0,
        "secondDoses": 121619,
        "secondDosesPercentageRaw": "90%",
        "secondDosesTo90Percent": 550,
        "totalPopulation": 135743
      },
      {
        "dhbName": "West Coast",
        "firstDoses": 25434,
        "firstDosesPercentageRaw": "91%",
        "firstDosesTo90Percent": 0,
        "secondDoses": 23872,
        "secondDosesPercentageRaw": "86%",
        "secondDosesTo90Percent": 1243,
        "totalPopulation": 27906
      },
      {
        "dhbName": "Canterbury",
        "firstDoses": 471026,
        "firstDosesPercentageRaw": "98%",
        "firstDosesTo90Percent": 0,
        "secondDoses": 453873,
        "secondDosesPercentageRaw": "94%",
        "secondDosesTo90Percent": 0,
        "totalPopulation": 482890
      },
      {
        "dhbName": "South Canterbury",
        "firstDoses": 49099,
        "firstDosesPercentageRaw": "93%",
        "firstDosesTo90Percent": 0,
        "secondDoses": 47046,
        "secondDosesPercentageRaw": "89%",
        "secondDosesTo90Percent": 280,
        "totalPopulation": 52584
      },
      {
        "dhbName": "Southern",
        "firstDoses": 276973,
        "firstDosesPercentageRaw": "96%",
        "firstDosesTo90Percent": 0,
        "secondDoses": 266188,
        "secondDosesPercentageRaw": "92%",
        "secondDosesTo90Percent": 0,
        "totalPopulation": 288015
      },
      {
        "dhbName": "Overseas / Unknown",
        "firstDoses": 2832,
        "firstDosesPercentageRaw": "16%",
        "firstDosesTo90Percent": 12624,
        "secondDoses": 2648,
        "secondDosesPercentageRaw": "15%",
        "secondDosesTo90Percent": 12808,
        "totalPopulation": 17173
      }
    ],
    "dataValidAsAtNzTimeIso": "2021-12-19T23:59:00.000+13:00"
  }
}